ansys/api/acp/VERSION
ansys/api/acp/__init__.py
ansys/api/acp/py.typed
ansys/api/acp/internal/event.proto
ansys/api/acp/internal/event_pb2.py
ansys/api/acp/internal/event_pb2.pyi
ansys/api/acp/internal/event_pb2_grpc.py
ansys/api/acp/internal/event_pb2_grpc.pyi
ansys/api/acp/internal/tree.proto
ansys/api/acp/internal/tree_pb2.py
ansys/api/acp/internal/tree_pb2.pyi
ansys/api/acp/internal/tree_pb2_grpc.py
ansys/api/acp/internal/tree_pb2_grpc.pyi
ansys/api/acp/v0/analysis_ply.proto
ansys/api/acp/v0/analysis_ply_pb2.py
ansys/api/acp/v0/analysis_ply_pb2.pyi
ansys/api/acp/v0/analysis_ply_pb2_grpc.py
ansys/api/acp/v0/analysis_ply_pb2_grpc.pyi
ansys/api/acp/v0/array_types.proto
ansys/api/acp/v0/array_types_pb2.py
ansys/api/acp/v0/array_types_pb2.pyi
ansys/api/acp/v0/array_types_pb2_grpc.py
ansys/api/acp/v0/array_types_pb2_grpc.pyi
ansys/api/acp/v0/base.proto
ansys/api/acp/v0/base_pb2.py
ansys/api/acp/v0/base_pb2.pyi
ansys/api/acp/v0/base_pb2_grpc.py
ansys/api/acp/v0/base_pb2_grpc.pyi
ansys/api/acp/v0/boolean_selection_rule.proto
ansys/api/acp/v0/boolean_selection_rule_pb2.py
ansys/api/acp/v0/boolean_selection_rule_pb2.pyi
ansys/api/acp/v0/boolean_selection_rule_pb2_grpc.py
ansys/api/acp/v0/boolean_selection_rule_pb2_grpc.pyi
ansys/api/acp/v0/butt_joint_sequence.proto
ansys/api/acp/v0/butt_joint_sequence_pb2.py
ansys/api/acp/v0/butt_joint_sequence_pb2.pyi
ansys/api/acp/v0/butt_joint_sequence_pb2_grpc.py
ansys/api/acp/v0/butt_joint_sequence_pb2_grpc.pyi
ansys/api/acp/v0/cad_component.proto
ansys/api/acp/v0/cad_component_pb2.py
ansys/api/acp/v0/cad_component_pb2.pyi
ansys/api/acp/v0/cad_component_pb2_grpc.py
ansys/api/acp/v0/cad_component_pb2_grpc.pyi
ansys/api/acp/v0/cad_geometry.proto
ansys/api/acp/v0/cad_geometry_pb2.py
ansys/api/acp/v0/cad_geometry_pb2.pyi
ansys/api/acp/v0/cad_geometry_pb2_grpc.py
ansys/api/acp/v0/cad_geometry_pb2_grpc.pyi
ansys/api/acp/v0/control.proto
ansys/api/acp/v0/control_pb2.py
ansys/api/acp/v0/control_pb2.pyi
ansys/api/acp/v0/control_pb2_grpc.py
ansys_api_acp-0.3.1.dist-info/licenses/AUTHORS
ansys_api_acp-0.3.1.dist-info/licenses/LICENSE
ansys_api_acp-0.3.1.dist-info/METADATA
ansys_api_acp-0.3.1.dist-info/WHEEL
ansys_api_acp-0.3.1.dist-info/entry_points.txt
ansys_api_acp-0.3.1.dist-info/top_level.txt
ansys_api_acp-0.3.1.dist-info/RECORD
