Metadata-Version: 2.4
Name: ansys-api-acp
Version: 0.3.1
Summary: Autogenerated Python package for the Ansys Composite PrepPost (ACP) gRPC API.
Home-page: https://github.com/ansys/ansys-api-acp
Author: ANSYS, Inc.
Author-email: pyansys.core@ansys.com
License: MIT
Project-URL: Documentation, https://github.com/ansys/ansys-api-acp/#readme
Project-URL: Source, https://github.com/ansys/ansys-api-acp/
Project-URL: Tracker, https://github.com/ansys/ansys-api-acp/issues/
Requires-Python: >=3.7
License-File: LICENSE
License-File: AUTHORS
Requires-Dist: grpcio~=1.17
Requires-Dist: protobuf<7,>=3.19
Dynamic: author
Dynamic: author-email
Dynamic: description
Dynamic: description-content-type
Dynamic: home-page
Dynamic: license
Dynamic: license-file
Dynamic: project-url
Dynamic: requires-dist
Dynamic: requires-python
Dynamic: summary
